nordlys_core/__init__.py
nordlys_core/__init__.pyi
nordlys_core/_core.cpython-312-x86_64-linux-gnu.so
nordlys_core/_core.pyi
nordlys_core/bindings.h
nordlys_core/checkpoint.cpp
nordlys_core/helpers.cpp
nordlys_core/helpers.h
nordlys_core/module.cpp
nordlys_core/nordlys.cpp
nordlys_core/results.cpp
nordlys_core/types.cpp
nordlys_core/include/module.modulemap
nordlys_core/include/nordlys.h
nordlys_core/include/nordlys/checkpoint/cache.hpp
nordlys_core/include/nordlys/checkpoint/checkpoint.hpp
nordlys_core/include/nordlys/clustering/cluster.hpp
nordlys_core/include/nordlys/clustering/cluster_cpu.hpp
nordlys_core/include/nordlys/clustering/cluster_cuda.hpp
nordlys_core/include/nordlys/clustering/embedding_view.hpp
nordlys_core/include/nordlys/clustering/cuda/common.cuh
nordlys_core/include/nordlys/clustering/cuda/config.cuh
nordlys_core/include/nordlys/clustering/cuda/distance.cuh
nordlys_core/include/nordlys/clustering/cuda/memory.cuh
nordlys_core/include/nordlys/clustering/cuda/memory_pool.cuh
nordlys_core/include/nordlys/clustering/cuda/reduce.cuh
nordlys_core/include/nordlys/clustering/cuda/utils.cuh
nordlys_core/include/nordlys/common/device.hpp
nordlys_core/include/nordlys/common/matrix.hpp
nordlys_core/include/nordlys/common/result.hpp
nordlys_core/include/nordlys/routing/nordlys.hpp
nordlys_core/include/nordlys/scoring/scorer.hpp
nordlys_core/include/simsimd/binary.h
nordlys_core/include/simsimd/curved.h
nordlys_core/include/simsimd/dot.h
nordlys_core/include/simsimd/elementwise.h
nordlys_core/include/simsimd/geospatial.h
nordlys_core/include/simsimd/mesh.h
nordlys_core/include/simsimd/probability.h
nordlys_core/include/simsimd/simsimd.h
nordlys_core/include/simsimd/sparse.h
nordlys_core/include/simsimd/spatial.h
nordlys_core/include/simsimd/types.h
nordlys_core/lib/libnordlys_c.so
nordlys_core/lib/libnordlys_c.so.0
nordlys_core/lib/libnordlys_c.so.0.2.8
nordlys_core/lib/libnordlys_checkpoint.a
nordlys_core_cu12-0.2.8.dist-info/METADATA
nordlys_core_cu12-0.2.8.dist-info/WHEEL
nordlys_core_cu12-0.2.8.dist-info/RECORD
nordlys_core_cu12-0.2.8.dist-info/sboms/auditwheel.cdx.json
