Metadata-Version: 2.2
Name: nordlys-core-cu12
Version: 0.2.8
Summary: C++ inference core for Nordlys (CUDA 12.x)
